setup.py
speedy/__init__.py
speedy/common.py
speedy/core.pyx
speedy/mpi.py
speedy/util.py
speedy/zeromq.py
speedy.egg-info/PKG-INFO
speedy.egg-info/SOURCES.txt
speedy.egg-info/dependency_links.txt
speedy.egg-info/requires.txt
speedy.egg-info/top_level.txt
test/test_rpc.py