Metadata-Version: 1.0
Name: speedy
Version: 0.23
Summary: Fast, non-blocking RPC system.
Home-page: http://github.com/rjpower/speedy
Author: Russell Power
Author-email: power@cs.nyu.edu
License: BSD
Platform: UNKNOWN
